cli/__init__.py
cli/cli.py
eaasi_uvi_client/__init__.py
eaasi_uvi_client/eaasi_uvi_client.py
eaasi_uvi_client-0.1.0.dist-info/LICENSE
eaasi_uvi_client-0.1.0.dist-info/METADATA
eaasi_uvi_client-0.1.0.dist-info/WHEEL
eaasi_uvi_client-0.1.0.dist-info/entry_points.txt
eaasi_uvi_client-0.1.0.dist-info/top_level.txt
eaasi_uvi_client-0.1.0.dist-info/RECORD
