Metadata-Version: 2.1
Name: eaasi-uvi-client
Version: 0.1.0
Summary: Python client to get emulation environment recommendations from the EaaSI UVI.
Home-page: https://github.com/artefactual-labs/eaasi-uvi-client
Author: Artefactual Systems, Inc.
Author-email: info@artefactual.com
License: Apache License 2.0
Platform: UNKNOWN
Classifier: Programming Language :: Python :: 3
Classifier: License :: OSI Approved :: GNU Affero General Public License v3
Classifier: Operating System :: OS Independent
Requires-Python: >=3.6
Requires-Dist: Click
Requires-Dist: requests
